slipbox/__init__.py
slipbox/__main__.py
slipbox/app.py
slipbox/batch.py
slipbox/build.py
slipbox/check.py
slipbox/cli.py
slipbox/commands.py
slipbox/config.py
slipbox/data.py
slipbox/database.py
slipbox/dependencies.py
slipbox/errors.py
slipbox/generator.py
slipbox/graph.py
slipbox/page.py
slipbox/processor.py
slipbox/profiler.py
slipbox/serializer.py
slipbox/templates.py
slipbox/utils.py
slipbox/data/README.md
slipbox/data/default.csl
slipbox/data/filter.lua
slipbox/data/slipbox.css
slipbox/data/slipbox.css.map
slipbox/data/slipbox.js
slipbox/data/slipbox.js.map
slipbox/data/svgo.config.js
slipbox/data/es5/core.js
slipbox/data/es5/latest.js
slipbox/data/es5/loader.js
slipbox/data/es5/mml-chtml.js
slipbox/data/es5/mml-svg.js
slipbox/data/es5/node-main.js
slipbox/data/es5/startup.js
slipbox/data/es5/tex-chtml-full-speech.js
slipbox/data/es5/tex-chtml-full.js
slipbox/data/es5/tex-chtml.js
slipbox/data/es5/tex-mml-chtml.js
slipbox/data/es5/tex-mml-svg.js
slipbox/data/es5/tex-svg-full.js
slipbox/data/es5/tex-svg.js
slipbox/data/es5/a11y/assistive-mml.js
slipbox/data/es5/a11y/complexity.js
slipbox/data/es5/a11y/explorer.js
slipbox/data/es5/a11y/semantic-enrich.js
slipbox/data/es5/a11y/sre.js
slipbox/data/es5/adaptors/liteDOM.js
slipbox/data/es5/input/asciimath.js
slipbox/data/es5/input/mml.js
slipbox/data/es5/input/tex-base.js
slipbox/data/es5/input/tex-full.js
slipbox/data/es5/input/tex.js
slipbox/data/es5/input/mml/entities.js
slipbox/data/es5/input/mml/extensions/mml3.js
slipbox/data/es5/input/mml/extensions/mml3.sef.json
slipbox/data/es5/input/tex/extensions/action.js
slipbox/data/es5/input/tex/extensions/all-packages.js
slipbox/data/es5/input/tex/extensions/ams.js
slipbox/data/es5/input/tex/extensions/amscd.js
slipbox/data/es5/input/tex/extensions/autoload.js
slipbox/data/es5/input/tex/extensions/bbox.js
slipbox/data/es5/input/tex/extensions/boldsymbol.js
slipbox/data/es5/input/tex/extensions/braket.js
slipbox/data/es5/input/tex/extensions/bussproofs.js
slipbox-0.19.14.dist-info/LICENSE
slipbox-0.19.14.dist-info/METADATA
slipbox-0.19.14.dist-info/WHEEL
slipbox-0.19.14.dist-info/entry_points.txt
slipbox-0.19.14.dist-info/top_level.txt
slipbox-0.19.14.dist-info/RECORD
