Metadata-Version: 2.1
Name: slipbox
Version: 0.19.14
Summary: Static site generator for Zettelkasten notes
Home-page: https://github.com/lggruspe/slipbox
Author: Levi Gruspe
Author-email: mail.levig@gmail.com
Classifier: Environment :: Console
Classifier: License :: OSI Approved :: MIT License
Classifier: Programming Language :: Python :: 3.8
Classifier: Programming Language :: Python :: 3.9
Classifier: Programming Language :: Python :: 3.10
Classifier: Programming Language :: Python :: 3.11
Requires-Python: >=3.8
License-File: LICENSE
Requires-Dist: colorama (>=0.4.6)
Requires-Dist: networkx (>=3.0)
Requires-Dist: pydot (>=1.4.2)
Requires-Dist: pyquery (>=2.0.0)
